reven_plugin_etube/__init__.py
reven_plugin_etube/crypto.py
reven_plugin_etube/fwinfo.py
reven_plugin_etube/hexpat.py
reven_plugin_etube-0.1.2.dist-info/licenses/LICENSE
reven_plugin_etube-0.1.2.dist-info/METADATA
reven_plugin_etube-0.1.2.dist-info/WHEEL
reven_plugin_etube-0.1.2.dist-info/top_level.txt
reven_plugin_etube-0.1.2.dist-info/RECORD
