Metadata-Version: 2.4
Name: reven-plugin-etube
Version: 0.1.2
Summary: Reven plugin for reverse engineering Shimano E-Tube firmware.
Author-email: Magnust Hektoen Steensland <mag.steensland@gmail.com>, Norbert Arkadiusz Görke <me@ngorke.dev>
License-Expression: Apache-2.0
Project-URL: Repository, https://github.com/reven-project/reven-plugin-etube.git
Keywords: reverse engineering
License-File: LICENSE
Requires-Dist: pycryptodome~=3.23
Requires-Dist: attrs~=25.3
Requires-Dist: typer~=0.16.0
Dynamic: license-file
